README
setup.cfg
setup.py
augur/VERSION
augur/__init__.py
augur/api.py
augur/check.py
augur/common.py
augur/context.py
augur/db.py
augur/serializers.py
augur/settings.py
augur/integrations/__init__.py
augur/integrations/augurgithub.py
augur/integrations/augurjira.py
augur/integrations/objects/__init__.py
augur/integrations/objects/base.py
augur/integrations/objects/board.py
augur/integrations/objects/issue.py
augur/integrations/objects/metrics.py
augur/integrations/objects/person.py
augur/proxies/__init__.py
augur/proxies/base.py
augur/proxies/path.py
augurlib.egg-info/PKG-INFO
augurlib.egg-info/SOURCES.txt
augurlib.egg-info/dependency_links.txt
augurlib.egg-info/requires.txt
augurlib.egg-info/top_level.txt