Metadata-Version: 2.1
Name: augurlib
Version: 1.1.61
Summary: A library for extracting actionable data from development tools 
Home-page: https://github.com/augur-ecosystem/augur/tree/master
Author: Karim Shehadeh
Author-email: karim@karim.cloud
License: MIT
Keywords: metrics jira github development
Platform: UNKNOWN
Classifier: Development Status :: 5 - Production/Stable
Classifier: Intended Audience :: Developers
Classifier: License :: OSI Approved :: MIT License
Classifier: Programming Language :: Python :: 3
Provides-Extra: dev
Provides-Extra: test
